Metadata-Version: 2.1
Name: datasette-base64
Version: 0.1
Summary: SQL functions to decode and encode base64 strings
Home-page: https://github.com/alberto-salinas/datasette-base64
Author: Jose Rodriguez Salinas
License: Apache License, Version 2.0
Project-URL: Issues, https://github.com/alberto-salinas/datasette-base64/issues
Project-URL: CI, https://github.com/alberto-salinas/datasette-base64/actions
Project-URL: Changelog, https://github.com/alberto-salinas/datasette-base64/releases
Platform: UNKNOWN
Requires-Python: >=3.6
Provides-Extra: test
